<?xml version = '1.0' encoding = 'UTF-8'?>
<TableProxyOraclev20c class="oracle.dbtools.crest.model.design.storage.oracle.v20c.TableProxyOraclev20c" name="`Monitors`" directorySegmentName="seg_0" id="5AAD094B-95D5-33E3-8BBC-32FA0160E018">
<createdBy>a1930</createdBy>
<createdTime>2024-03-31 06:35:10 UTC</createdTime>
<ownerDesignName>model</ownerDesignName>
<logging>YES</logging>
<partitionedRowMovement>DISABLE</partitionedRowMovement>
<temporaryChanged>false</temporaryChanged>
<accessDriverType>oracle_loader</accessDriverType>
<rejectLimit></rejectLimit>
<columnProxies itemClass="oracle.dbtools.crest.model.design.storage.oracle.v12c.ColumnProxyOraclev12c">
<ColumnProxy name="KEY" id="40BD7E94-1F58-9A15-F5E5-18A33739AB1A">
<createdBy>a1930</createdBy>
<createdTime>2024-03-31 06:35:10 UTC</createdTime>
<ownerDesignName>model</ownerDesignName>
</ColumnProxy>
<ColumnProxy name="`Datу_use`" id="59CBB15B-7AD2-A28D-8EC6-98C005EB3E74">
<createdBy>a1930</createdBy>
<createdTime>2024-03-31 06:35:10 UTC</createdTime>
<ownerDesignName>model</ownerDesignName>
</ColumnProxy>
<ColumnProxy name="`Inventory_number`" id="A44EF96A-7089-90FC-8FAB-8753BC2FF09E">
<createdBy>a1930</createdBy>
<createdTime>2024-03-31 06:35:10 UTC</createdTime>
<ownerDesignName>model</ownerDesignName>
</ColumnProxy>
<ColumnProxy name="`Employees`_`EmployeeID`" id="B04DE701-842B-8661-0086-1951646B4390">
<createdBy>a1930</createdBy>
<createdTime>2024-03-31 06:35:10 UTC</createdTime>
<ownerDesignName>model</ownerDesignName>
</ColumnProxy>
<ColumnProxy name="`Model`" id="BDAF0FA1-E9E4-4F9D-3BB8-F322D387313E">
<createdBy>a1930</createdBy>
<createdTime>2024-03-31 06:35:10 UTC</createdTime>
<ownerDesignName>model</ownerDesignName>
</ColumnProxy>
<ColumnProxy name="`Connectors`" id="CD84AD56-627D-0941-3FF6-ADC88F4C7161">
<createdBy>a1930</createdBy>
<createdTime>2024-03-31 06:35:10 UTC</createdTime>
<ownerDesignName>model</ownerDesignName>
</ColumnProxy>
<ColumnProxy name="UNIQUE" id="CF61717E-FCAD-78EA-45AE-2F6BB46F345A">
<createdBy>a1930</createdBy>
<createdTime>2024-03-31 06:35:10 UTC</createdTime>
<ownerDesignName>model</ownerDesignName>
</ColumnProxy>
<ColumnProxy name="`Status`" id="D85C1572-5DD1-6C14-97A4-7011B7B90125">
<createdBy>a1930</createdBy>
<createdTime>2024-03-31 06:35:10 UTC</createdTime>
<ownerDesignName>model</ownerDesignName>
</ColumnProxy>
<ColumnProxy name="`Screen`" id="EDF6B138-A7E9-69A0-A9F9-E9A800EAD6BD">
<createdBy>a1930</createdBy>
<createdTime>2024-03-31 06:35:10 UTC</createdTime>
<ownerDesignName>model</ownerDesignName>
</ColumnProxy>
<ColumnProxy name="`SerialNumber`" id="FE90B9D8-9EF7-DDB6-C536-B5CE80F8A5FB">
<createdBy>a1930</createdBy>
<createdTime>2024-03-31 06:35:10 UTC</createdTime>
<ownerDesignName>model</ownerDesignName>
</ColumnProxy>
</columnProxies>
<foreignKeys>
<ForeignKey class="oracle.dbtools.crest.model.design.storage.oracle.v10g.FKProxyOraclev10g" name="`Monitors`_`Employees`_FK" id="96515079-683F-3D07-9272-88FC4E4154A1">
<createdBy>a1930</createdBy>
<createdTime>2024-03-31 06:35:10 UTC</createdTime>
<ownerDesignName>model</ownerDesignName>
</ForeignKey>
</foreignKeys>
<primaryKeys>
<PrimaryKey class="oracle.dbtools.crest.model.design.storage.oracle.v10g.PKProxyOraclev10g" name="`Monitors`_PK" id="30F0257B-CC04-CDD6-76CB-4380B09D44D5">
<createdBy>a1930</createdBy>
<createdTime>2024-03-31 06:35:10 UTC</createdTime>
<ownerDesignName>model</ownerDesignName>
<indexSort>SORTED</indexSort>
</PrimaryKey>
</primaryKeys>
</TableProxyOraclev20c>